darca_repository/__init__.py
darca_repository/__version__.py
darca_repository/exceptions.py
darca_repository/instance.py
darca_repository/models.py
darca_repository/registry/__init__.py
darca_repository/registry/base.py
darca_repository/registry/factory.py
darca_repository/registry/mysql_registry.py
darca_repository/registry/yaml_registry.py
darca_repository-0.0.1.dist-info/LICENSE
darca_repository-0.0.1.dist-info/METADATA
darca_repository-0.0.1.dist-info/WHEEL
darca_repository-0.0.1.dist-info/RECORD
