Metadata-Version: 2.3
Name: darca-repository
Version: 0.0.1
Summary: Darca repository management library
License: LICENSE
Author: Roel Kist
Author-email: roel.kist@gmail.com
Requires-Python: >=3.12,<4.0
Classifier: License :: Other/Proprietary License
Classifier: Programming Language :: Python :: 3
Classifier: Programming Language :: Python :: 3.12
Classifier: Programming Language :: Python :: 3.13
Requires-Dist: darca-exception (>=0.1.1,<0.2.0)
Requires-Dist: darca-storage (>=0.0.1,<0.0.2)
Requires-Dist: pydantic (>=2.11.4,<3.0.0)
Requires-Dist: typing-extensions (>=4.13.2,<5.0.0)
